langgraph_log_parser/__init__.py
langgraph_log_parser/analyze.py
langgraph_log_parser/analyze_case_id.py
langgraph_log_parser/artifacts.py
langgraph_log_parser/create_html.py
langgraph_log_parser/create_report.py
langgraph_log_parser/experiment.py
langgraph_log_parser/graph_runner.py
langgraph_log_parser/jsons_to_csv.py
langgraph_log_parser/load_events.py
langgraph_log_parser/sql_to_jsons.py
langgraph_log_parser/templates/comparison_report.html
langgraph_log_parser/templates/components/metrics.html
langgraph_log_parser/templates/components/modal.html
langgraph_log_parser/templates/components/scripts.html
langgraph_log_parser/templates/components/sequences.html
langgraph_log_parser/templates/components/styles.html
langgraph_log_parser/templates/components/visualizations.html
langgraph_log_parser/visualize.py
langgraph_log_parser-0.1.14.dist-info/LICENSE
langgraph_log_parser-0.1.14.dist-info/METADATA
langgraph_log_parser-0.1.14.dist-info/WHEEL
langgraph_log_parser-0.1.14.dist-info/RECORD
